friendlypins/__init__.py
friendlypins/api.py
friendlypins/board.py
friendlypins/headers.py
friendlypins/pin.py
friendlypins/thumbnail.py
friendlypins/user.py
friendlypins/version.py
friendlypins/scripts/__init__.py
friendlypins/scripts/fpins.py
friendlypins/scripts/webp2jpeg.py
friendlypins/utils/__init__.py
friendlypins/utils/console_actions.py
friendlypins/utils/rest_io.py
friendlypins-1.0.4.dist-info/DESCRIPTION.rst
friendlypins-1.0.4.dist-info/METADATA
friendlypins-1.0.4.dist-info/RECORD
friendlypins-1.0.4.dist-info/WHEEL
friendlypins-1.0.4.dist-info/entry_points.txt
friendlypins-1.0.4.dist-info/metadata.json
friendlypins-1.0.4.dist-info/top_level.txt
