Metadata-Version: 2.0
Name: friendlypins
Version: 1.0.4
Summary: Python wrapper around the Pinterest developer APIs
Home-page: https://github.com/TheFriendlyCoder/friendlypins
Author: Kevin S. Phillips
Author-email: thefriendlycoder@gmail.com
License: Apache License 2.0
Keywords: pinterest api wrapper library
Platform: UNKNOWN
Classifier: Development Status :: 3 - Alpha
Classifier: Environment :: Console
Classifier: License :: OSI Approved :: Apache Software License
Classifier: Topic :: Software Development :: Libraries
Classifier: Natural Language :: English
Classifier: Operating System :: OS Independent
Classifier: Programming Language :: Python :: 2
Classifier: Programming Language :: Python :: 3
Requires-Python: >=2.7, !=3.0.*, !=3.1.*, !=3.2.*, !=3.3.*, <4
Requires-Dist: requests
Requires-Dist: six
Requires-Dist: dateutils
Requires-Dist: tqdm
Requires-Dist: pillow
Provides-Extra: dev
Requires-Dist: twine; extra == 'dev'
Requires-Dist: pytest; extra == 'dev'
Requires-Dist: pytest-cov; extra == 'dev'
Requires-Dist: mock; extra == 'dev'
Requires-Dist: pylint; extra == 'dev'
Requires-Dist: sphinx; extra == 'dev'
Requires-Dist: tox; extra == 'dev'
Requires-Dist: radon; extra == 'dev'
